package/__init__.py
package/cities.json
package/file.py
package/states_info.py
package/my_folder/__init__.py
package/my_folder/my_nested_file.py
my_package_jithish-0.0.5.dist-info/LICENSE
my_package_jithish-0.0.5.dist-info/METADATA
my_package_jithish-0.0.5.dist-info/WHEEL
my_package_jithish-0.0.5.dist-info/top_level.txt
my_package_jithish-0.0.5.dist-info/RECORD
